{
  "name": "J.Crew",
  "category": [
    "clothing_store",
    "shoe_store",
    "store",
    "point_of_interest",
    "establishment"
  ],
  "latitude": 40.7591141,
  "longitude": -73.97900729999999,
  "description": null,
  "image": {
    "name": "J",
    "file_name": "J.Crew",
    "url": "//s3.amazonaws.com/cdn.dev-traveltripper.info/site-assets/1_40_87/media/2018-08-02-032209/2017-07-19.png",
    "tags": "",
    "description": "",
    "date_added": "2018-08-02-032209",
    "file_type": "image/jpeg",
    "width": 1200,
    "height": 1600,
    "file_size": 2507514,
    "url_large": "//s3.amazonaws.com/cdn.dev-traveltripper.info/site-assets/1_40_87/media/2018-08-02-032209/large_2017-07-19.png",
    "url_medium": "//s3.amazonaws.com/cdn.dev-traveltripper.info/site-assets/1_40_87/media/2018-08-02-032209/medium_2017-07-19.png",
    "url_small": "//s3.amazonaws.com/cdn.dev-traveltripper.info/site-assets/1_40_87/media/2018-08-02-032209/small_2017-07-19.png",
    "url_xsmall": "//s3.amazonaws.com/cdn.dev-traveltripper.info/site-assets/1_40_87/media/2018-08-02-032209/xsmall_2017-07-19.png",
    "url_thumb": "//s3.amazonaws.com/cdn.dev-traveltripper.info/site-assets/1_40_87/media/2018-08-02-032209/thumb_2017-07-19.png"
  },
  "location": {
    "latitude": null,
    "longitude": -73.97900729999999,
    "vicinity": "30 Rockefeller Plaza, New York",
    "place_id": "ChIJNZvR1v5YwokR8xZLn8p83Sk"
  }
}